ywkd_tools/__init__.py
ywkd_tools/logger.py
ywkd_tools/utils.py
ywkd_tools/auth/__init__.py
ywkd_tools/auth/auth.py
ywkd_tools/auth/decorators.py
ywkd_tools/inner_service_apis/__init__.py
ywkd_tools/inner_service_apis/errors.py
ywkd_tools/inner_service_apis/inner_service_apis.py
ywkd_tools/inner_service_apis/cperm/__init__.py
ywkd_tools/inner_service_apis/cperm/interface.py
ywkd_tools/inner_service_apis/msg/__init__.py
ywkd_tools/inner_service_apis/msg/interface.py
ywkd_tools/inner_service_apis/participant/__init__.py
ywkd_tools/inner_service_apis/participant/interface.py
ywkd_tools-1.0.18.dist-info/LICENSE
ywkd_tools-1.0.18.dist-info/METADATA
ywkd_tools-1.0.18.dist-info/WHEEL
ywkd_tools-1.0.18.dist-info/top_level.txt
ywkd_tools-1.0.18.dist-info/RECORD
