Metadata-Version: 2.1
Name: ywkd-tools
Version: 1.0.18
Summary: 娱网科道内部python 公用包
Home-page: UNKNOWN
Author: ywkd
Author-email: 
License: UNKNOWN
Platform: UNKNOWN
Classifier: Programming Language :: Python :: 3
Classifier: License :: OSI Approved :: MIT License
Classifier: Operating System :: OS Independent
Requires-Python: >=3.4
Requires-Dist: django
Requires-Dist: djangorestframework (<4,>=3)
Requires-Dist: django-log-request-id
